{"data":{"ModuleTitle":{"label":"Module Title","value":"Company Description"},"CompanyName":{"label":"Company Name","value":"3 E Network Technology Group Ltd"},"Symbol":{"label":"Symbol","value":"MASK"},"Address":{"label":"Address","value":"UNIT 1005,10/F, TOWER A,NEW MANDARIN PLAZA,14 SCIENCE MUSEUM RO, TIM SHA TSUI, Hong Kong"},"Phone":{"label":"Phone","value":""},"Industry":{"label":"Industry","value":"EDP Services"},"Sector":{"label":"Sector","value":"Technology"},"Region":{"label":"Region","value":"Asia"},"CompanyDescription":{"label":"Company Description","value":"3 E Network Technology is a business-to-business information technology business solutions provider. Through our two PRC subsidiaries, Guangzhou Sanyi Network and Guangzhou 3E Network, we started as a business that focuses on integrated software solutions in the property management and exhibition services spaces, but expanded our software solution offering to reach across a variety of industries and sectors, including food establishments, real estate, exhibition & conferencing, and clean energy utilities. Guangzhou Sanyi Network primarily serves our software development and exhibition and conference portfolios, while Guangzhou 3E Network primarily focuses on expanding into the clean energy sector."},"CompanyUrl":{"label":"Company Url","value":null}},"message":null,"status":{"rCode":200,"bCodeMessage":null,"developerMessage":null}}