{"data":{"ModuleTitle":{"label":"Module Title","value":"Company Description"},"CompanyName":{"label":"Company Name","value":"Klarna Group plc Ordinary Shares"},"Symbol":{"label":"Symbol","value":"KLAR"},"Address":{"label":"Address","value":"10 YORK ROAD,LONDON SE1 7ND, LONDON, SE1 7ND, United Kingdom"},"Phone":{"label":"Phone","value":""},"Industry":{"label":"Industry","value":null},"Sector":{"label":"Sector","value":null},"Region":{"label":"Region","value":null},"CompanyDescription":{"label":"Company Description","value":"Klarna Group is a technology company building the next-generation commerce network. We have built one of the largest commerce networks in the world, measured by the number of consumers and merchants, serving approximately 93 million active Klarna consumers and more than 675,000 merchants in 26 countries. Our flexible and personalized products, trusted consumer brand, global distribution and proprietary scalable infrastructure are the foundations enabling us to become our consumers' everyday spending and saving partner, available everywhere and for everything. Through our history, we have consistently innovated and challenged the status quo, evolving our network from a consumer-focused payments tool to a global commerce network that enables merchant success."},"CompanyUrl":{"label":"Company Url","value":null}},"message":null,"status":{"rCode":200,"bCodeMessage":null,"developerMessage":null}}