{"data":{"ModuleTitle":{"label":"Module Title","value":"Company Description"},"CompanyName":{"label":"Company Name","value":"AsiaStrategy"},"Symbol":{"label":"Symbol","value":"SORA"},"Address":{"label":"Address","value":"33/F SUNSHINE PLAZA 353 LOCKHART ROAD, WAN CHAI, Hong Kong"},"Phone":{"label":"Phone","value":""},"Industry":{"label":"Industry","value":"Other Specialty Stores"},"Sector":{"label":"Sector","value":"Industrials"},"Region":{"label":"Region","value":"Asia"},"CompanyDescription":{"label":"Company Description","value":"AsiaStrategy Trading is a wholesaler engaged in trading, distribution, and retail of luxury watches of international brands. As the purveyor of fine watches, we source luxury products directly or indirectly from authorized dealers, distributors, and brand owners, located in Europe, Japan, Singapore, and other locations, and sell them to our customers, comprising independent watch dealers, watch distributors, and retail buyers within the watch industry. Our strategic location in Hong Kong positions us advantageously within the Asia-Pacific luxury market. We currently offer a selection of over 30 internationally renowned watch brands, including Blancpain, Breguet, Cartier, Chopard, Hermes, IWC, Jaeger, Rolex, Omega, and Longines. We primarily trade watches within the price range of 1,900 to 7,500 with our target customers being middle to high-income earners."},"CompanyUrl":{"label":"Company Url","value":null}},"message":null,"status":{"rCode":200,"bCodeMessage":null,"developerMessage":null}}