{"data":{"ModuleTitle":{"label":"Module Title","value":"Company Description"},"CompanyName":{"label":"Company Name","value":"Brightstar Lottery PLC Trading under the Legal Name to begin at"},"Symbol":{"label":"Symbol","value":"BRSL"},"Address":{"label":"Address","value":"66 SEYMOUR STREET,2ND FLOOR, MARBLE ARCH HOUSE, LONDON, W1H 5BT, United Kingdom"},"Phone":{"label":"Phone","value":"+44 2075353200"},"Industry":{"label":"Industry","value":"Services-Misc. Amusement & Recreation"},"Sector":{"label":"Sector","value":"Consumer Discretionary"},"Region":{"label":"Region","value":"North America"},"CompanyDescription":{"label":"Company Description","value":"Brightstar is an innovative, forward-thinking global leader in lottery that builds on our renowned expertise in delivering secure technology and producing reliable, comprehensive solutions for our customers. As a premier pure play global lottery company, our best-in-class lottery operations, retail and digital solutions, and award-winning lottery games enable our customers to achieve their goals, fulfill player needs and distribute meaningful benefits to communities. Brightstar has a well-established local presence and is a trusted partner to governments and regulators around the world, creating value by adhering to the highest standards of service, integrity, and responsibility. Brightstar has approximately 6,000 employees."},"CompanyUrl":{"label":"Company Url","value":"https://www.igt.com"}},"message":null,"status":{"rCode":200,"bCodeMessage":null,"developerMessage":null}}