{"data":{"ModuleTitle":{"label":"Module Title","value":"Company Description"},"CompanyName":{"label":"Company Name","value":"Lithium Argentina AG"},"Symbol":{"label":"Symbol","value":"LAR"},"Address":{"label":"Address","value":"900 WEST HASTINGS STREET,SUITE 300, VANCOUVER, British Columbia, V6C 1E5, Canada"},"Phone":{"label":"Phone","value":"+1 778 656-5820"},"Industry":{"label":"Industry","value":"Metal Mining"},"Sector":{"label":"Sector","value":"Basic Materials"},"Region":{"label":"Region","value":"North America"},"CompanyDescription":{"label":"Company Description","value":"Lithium Argentina is a producer of lithium carbonate for use primarily in lithium-ion batteries and electric vehicles. The Company, in partnership with Ganfeng Lithium Co. Ltd, is operating the Cauchari-Olaroz lithium brine operation in Argentina and advancing development of additional lithium resources in the region."},"CompanyUrl":{"label":"Company Url","value":"https://www.lithium-argentina.com"}},"message":null,"status":{"rCode":200,"bCodeMessage":null,"developerMessage":null}}