{"data":{"ModuleTitle":{"label":"Module Title","value":"Company Description"},"CompanyName":{"label":"Company Name","value":"Beeline Holdings, Inc."},"Symbol":{"label":"Symbol","value":"BLNE"},"Address":{"label":"Address","value":"188 VALLEY STREET,,SUITE 225,, PROVIDENCE, Rhode Island, 02909, United States"},"Phone":{"label":"Phone","value":"+888 810-5760"},"Industry":{"label":"Industry","value":"Finance: Consumer Services"},"Sector":{"label":"Sector","value":"Finance"},"Region":{"label":"Region","value":"North America"},"CompanyDescription":{"label":"Company Description","value":"Beeline Holdings, Inc. is a pioneering mortgage fintech company with a digital, AI-powered lending and title platform. Headquartered in Providence, RI, Beeline is transforming home loans, making them simpler and faster so everyone can have more financial freedom through their property."},"CompanyUrl":{"label":"Company Url","value":"https://makeabeeline.com/about/"}},"message":null,"status":{"rCode":200,"bCodeMessage":null,"developerMessage":null}}